nanomqtt/__init__.py
nanomqtt/client.py
nanomqtt-0.1.0.dist-info/METADATA
nanomqtt-0.1.0.dist-info/WHEEL
nanomqtt-0.1.0.dist-info/top_level.txt
nanomqtt-0.1.0.dist-info/RECORD
