Metadata-Version: 2.4
Name: nanomqtt
Version: 0.1.0
Summary: A lightweight wrapper around Paho MQTT client
Author-email: NanoSievert <no@dontcontactme.com>
License: MIT
Requires-Python: >=3.8
Requires-Dist: paho-mqtt>=2.0.0
